PyCRA/__init__.py
PyCRA/__main__.py
PyCRA/_checker.py
PyCRA/files_content.py
PyCRA/messages.py
PyCRA/parser.py
py_cra-0.0.6.dist-info/LICENSE.txt
py_cra-0.0.6.dist-info/METADATA
py_cra-0.0.6.dist-info/WHEEL
py_cra-0.0.6.dist-info/top_level.txt
py_cra-0.0.6.dist-info/RECORD
