Metadata-Version: 2.1
Name: py-cra
Version: 0.0.6
Summary: Python tool to create an react web app for django or flask backend
Home-page: https://github.com/Moaz-Mohammed-Elesawey/py-cra
Author: Moaz Mohammed El-Esawey
Author-email: mohammedmiaz3141@gmail.com
License: UNKNOWN
Project-URL: Source, https://github.com/Moaz-Mohammed-Elesawey/py-cra
Keywords: react,frontend,python,pycra
Platform: UNKNOWN
Classifier: Development Status :: 5 - Production/Stable
Classifier: License :: OSI Approved :: MIT License
Classifier: Programming Language :: Python :: 3
Requires-Python: >=3.6, <4
